ncmlistdownloader/__init__.py
ncmlistdownloader/login.py
ncmlistdownloader/common/__init__.py
ncmlistdownloader/common/encode_sec_key.py
ncmlistdownloader/common/global_args.py
ncmlistdownloader/common/thread_test.py
ncmlistdownloader/common/version.py
ncmlistdownloader/downloader/__init__.py
ncmlistdownloader/downloader/json_list_io.py
ncmlistdownloader/editer/__init__.py
ncmlistdownloader/playlist/__init__.py
ncmlistdownloader/song/__init__.py
ncmlistdownloader-1.3.2.240707.dist-info/LICENSE
ncmlistdownloader-1.3.2.240707.dist-info/METADATA
ncmlistdownloader-1.3.2.240707.dist-info/WHEEL
ncmlistdownloader-1.3.2.240707.dist-info/entry_points.txt
ncmlistdownloader-1.3.2.240707.dist-info/top_level.txt
ncmlistdownloader-1.3.2.240707.dist-info/RECORD
